sofa_score_data/Scraper_Sofascore.py
sofa_score_data/__init__.py
sofa_score_data/transformations.py
sofa_score_data-0.4.0.dist-info/LICENSE
sofa_score_data-0.4.0.dist-info/WHEEL
sofa_score_data-0.4.0.dist-info/METADATA
sofa_score_data-0.4.0.dist-info/RECORD
