Metadata-Version: 2.1
Name: sofa_score_data
Version: 0.4.0
Summary: A template Python module
Home-page: https://github.com/niesfutbol/sofa_score_data
Author: NIES
Author-email: nepo@nies.futbol
Requires-Python: >=3.9
Classifier: License :: OSI Approved :: GNU General Public License v3 or later (GPLv3+)
Requires-Dist: pandas
